{"mean":{"confidence_interval":{"confidence_level":0.95,"lower_bound":70834.42858150472,"upper_bound":72480.89437664827},"point_estimate":71606.2915083097,"standard_error":423.0796371866513},"median":{"confidence_interval":{"confidence_level":0.95,"lower_bound":70619.07695924764,"upper_bound":72406.94723092999},"point_estimate":71369.26197318008,"standard_error":467.12003528441653},"median_abs_dev":{"confidence_interval":{"confidence_level":0.95,"lower_bound":398.13451022533167,"upper_bound":2291.0948925537805},"point_estimate":1241.1899727920663,"standard_error":482.3328623063276},"slope":{"confidence_interval":{"confidence_level":0.95,"lower_bound":70752.53005094043,"upper_bound":71621.15176596727},"point_estimate":71133.14414566624,"standard_error":220.14805304980456},"std_dev":{"confidence_interval":{"confidence_level":0.95,"lower_bound":642.2482276790533,"upper_bound":1878.7955213254304},"point_estimate":1410.115121530478,"standard_error":331.67710229432794}}